vertebrate/__init__.py
vertebrate/compute.py
vertebrate/builtins/__init__.py
vertebrate/builtins/htcondor.py
vertebrate/builtins/os.py
vertebrate/builtins/postgres.py
vertebrate/builtins/psql.py
vertebrate/builtins/python.py
vertebrate/builtins/ssh.py
vertebrate-0.1.1.dist-info/METADATA
vertebrate-0.1.1.dist-info/WHEEL
vertebrate-0.1.1.dist-info/licenses/LICENSE
vertebrate-0.1.1.dist-info/RECORD
