Metadata-Version: 2.4
Name: vertebrate
Version: 0.1.1
Summary: Open backbones for data architecture
Project-URL: Repository, https://github.com/glue-lab/vertebrate
Author-email: Matt Christie <christiemj09@gmail.com>
License: Copyright 2026 Global Land Use and Environment Lab
License-File: LICENSE
Requires-Python: >=3.11
Provides-Extra: htcondor
Requires-Dist: htcondor; extra == 'htcondor'
Provides-Extra: postgres
Requires-Dist: psycopg2-binary; extra == 'postgres'
Requires-Dist: sqlalchemy>=2; extra == 'postgres'
